waveform_editor/__init__.py
waveform_editor/annotations.py
waveform_editor/base_waveform.py
waveform_editor/cli.py
waveform_editor/configuration.py
waveform_editor/dependency_graph.py
waveform_editor/derived_waveform.py
waveform_editor/dict_editor.py
waveform_editor/exporter.py
waveform_editor/group.py
waveform_editor/muscle3.py
waveform_editor/pcssp_exporter.py
waveform_editor/settings.py
waveform_editor/util.py
waveform_editor/waveform.py
waveform_editor/yaml_globals.py
waveform_editor/yaml_parser.py
waveform_editor/gui/editor.py
waveform_editor/gui/main.py
waveform_editor/gui/plotter_edit.py
waveform_editor/gui/plotter_view.py
waveform_editor/gui/shape_editor.py
waveform_editor/gui/util.py
waveform_editor/gui/io/file_exporter.py
waveform_editor/gui/io/file_loader.py
waveform_editor/gui/io/file_saver.py
waveform_editor/gui/io/filebrowser.py
waveform_editor/gui/io/filedialog.py
waveform_editor/gui/io/manager.py
waveform_editor/gui/selector/confirm_modal.py
waveform_editor/gui/selector/options_button_row.py
waveform_editor/gui/selector/rename_modal.py
waveform_editor/gui/selector/selection_group.py
waveform_editor/gui/selector/selector.py
waveform_editor/gui/selector/text_input_form.py
waveform_editor/shape_editor/coil_currents.py
waveform_editor/shape_editor/nice_integration.py
waveform_editor/shape_editor/nice_plotter.py
waveform_editor/shape_editor/plasma_properties.py
waveform_editor/shape_editor/plasma_shape.py
waveform_editor/shape_editor/xml_param/direct_param.xml
waveform_editor/shape_editor/xml_param/inverse_param.xml
waveform_editor/tendencies/base.py
waveform_editor/tendencies/constant.py
waveform_editor/tendencies/linear.py
waveform_editor/tendencies/piecewise.py
waveform_editor/tendencies/repeat.py
waveform_editor/tendencies/smooth.py
waveform_editor/tendencies/util.py
waveform_editor/tendencies/periodic/periodic_base.py
waveform_editor/tendencies/periodic/sawtooth_wave.py
waveform_editor/tendencies/periodic/sine_wave.py
waveform_editor-0.3.1.dist-info/licenses/LICENSE.txt
waveform_editor-0.3.1.dist-info/METADATA
waveform_editor-0.3.1.dist-info/WHEEL
waveform_editor-0.3.1.dist-info/entry_points.txt
waveform_editor-0.3.1.dist-info/top_level.txt
waveform_editor-0.3.1.dist-info/RECORD
