Metadata-Version: 2.4
Name: waveform-editor
Version: 0.3.1
Summary: Python tool to create and edit 1D waveforms (time-varying signals)
Author: Waveform Editor Developers
License:                   GNU LESSER GENERAL PUBLIC LICENSE
Project-URL: homepage, https://github.com/iterorganization/Waveform-Editor
License-File: LICENSE.txt
Requires-Dist: numpy
Requires-Dist: pandas
Requires-Dist: click
Requires-Dist: matplotlib
Requires-Dist: scipy
Requires-Dist: imas-python[netcdf]
Requires-Dist: panel>=1.6.3
Requires-Dist: pygments
Requires-Dist: plotly
Requires-Dist: holoviews
Requires-Dist: ruamel.yaml
Requires-Dist: kaleido
Requires-Dist: asteval
Requires-Dist: muscle3
Provides-Extra: all
Requires-Dist: waveform-editor[dev,docs,linting,test]; extra == "all"
Provides-Extra: dev
Requires-Dist: waveform-editor[linting,test]; extra == "dev"
Requires-Dist: watchfiles; extra == "dev"
Provides-Extra: linting
Requires-Dist: ruff; extra == "linting"
Provides-Extra: test
Requires-Dist: pytest>=5.4.1; extra == "test"
Requires-Dist: pytest-cov>=0.6; extra == "test"
Requires-Dist: pytest-xdist; extra == "test"
Requires-Dist: pytest-randomly; extra == "test"
Provides-Extra: docs
Requires-Dist: waveform-editor[muscle3]; extra == "docs"
Requires-Dist: sphinx<7.0.0,>=6.0.0; extra == "docs"
Requires-Dist: sphinx-autosummary-accessors>=0.1.2; extra == "docs"
Requires-Dist: sphinx-immaterial<0.12,>=0.11.0; extra == "docs"
Dynamic: license-file
